repogather.py
repogather/__init__.py
repogather/file_filter.py
repogather/llm_query.py
repogather/openai_client.py
repogather/output_processor.py
repogather/repogather.py
repogather/token_counter.py
repogather-0.0.4.dist-info/LICENSE
repogather-0.0.4.dist-info/METADATA
repogather-0.0.4.dist-info/WHEEL
repogather-0.0.4.dist-info/entry_points.txt
repogather-0.0.4.dist-info/top_level.txt
repogather-0.0.4.dist-info/RECORD
