Metadata-Version: 2.1
Name: repogather
Version: 0.0.4
Summary: Easily copy all relevant source files in a repository to clipboard
Home-page: UNKNOWN
License: MIT
Platform: UNKNOWN
Requires-Python: >=3.7
License-File: LICENSE
Requires-Dist: tiktoken
Requires-Dist: pyperclip
Requires-Dist: requests
Requires-Dist: python-dotenv
